lpi_andor/__init__.py
lpi_andor/_version.py
lpi_andor/enums.py
lpi_andor/helpers.py
lpi_andor/measurement_parameters.py
lpi_andor/spectrometer.py
lpi_andor/package_data/sdk/Windows/32/atmcd32d.dll
lpi_andor/package_data/sdk/Windows/64/atmcd64d.dll
lpi_andor/package_data/spectrometer/Windows/32/atspectrograph.dll
lpi_andor/package_data/spectrometer/Windows/64/atspectrograph.dll
lpi_andor-0.0.3.post1.dist-info/LICENSE
lpi_andor-0.0.3.post1.dist-info/METADATA
lpi_andor-0.0.3.post1.dist-info/WHEEL
lpi_andor-0.0.3.post1.dist-info/top_level.txt
lpi_andor-0.0.3.post1.dist-info/RECORD
