Metadata-Version: 2.1
Name: lpi-andor
Version: 0.0.3.post1
Summary: Controller class for communicating with Andor Kymera spectrometers.
Home-page: UNKNOWN
Author: Brian Carlsen
Author-email: carlsen.bri@gmail.com
License: UNKNOWN
Project-URL: Source Code, https://github.com/EPFL-LPI/andor_controller
Project-URL: Bug Tracker, https://github.com/EPFL-LPI/andor_controller/issues
Keywords: andor,spectrometer
Platform: UNKNOWN
Classifier: Programming Language :: Python :: 3
Classifier: License :: OSI Approved :: GNU General Public License v3 (GPLv3)
Classifier: Operating System :: Microsoft :: Windows
Classifier: Development Status :: 3 - Alpha
Requires-Python: >=3.7
License-File: LICENSE
Requires-Dist: setuptools
Requires-Dist: pyAndorSpectrograph
Requires-Dist: pyAndorSDK2
